LICENSE.txt
MANIFEST.in
README.md
setup.py
src/pdef/__init__.py
src/pdef/descriptors.py
src/pdef/formats.py
src/pdef/invoke.py
src/pdef/rpc.py
src/pdef/types.py
src/pdef/version.py
src/pdef.egg-info/PKG-INFO
src/pdef.egg-info/SOURCES.txt
src/pdef.egg-info/dependency_links.txt
src/pdef.egg-info/requires.txt
src/pdef.egg-info/top_level.txt