Metadata-Version: 1.1
Name: pdef
Version: 1.2.0
Summary: Protocol definition language
Home-page: http://github.com/pdef/pdef-python
Author: Ivan Korobkov
Author-email: ivan.korobkov@gmail.com
License: Apache License 2.0
Platform: UNKNOWN
Classifier: Development Status :: 4 - Beta
Classifier: Intended Audience :: Developers
Classifier: License :: OSI Approved :: Apache Software License
Classifier: Operating System :: OS Independent
Classifier: Programming Language :: Python :: 2.7
Classifier: Topic :: Internet :: WWW/HTTP
Classifier: Topic :: Internet :: WWW/HTTP :: WSGI
Classifier: Topic :: Software Development :: Libraries
